beam/__init__.py
beam/app.py
beam/exceptions.py
beam/serializer.py
beam/templates/base.jinja
beam/type.py
beam/utils/__init__.py
beam/utils/build.py
beam/utils/init.py
beam/utils/parse.py
beam/utils/print.py
beam/validators.py
beam_sdk-0.15.14.dist-info/LICENSE
beam_sdk-0.15.14.dist-info/METADATA
beam_sdk-0.15.14.dist-info/WHEEL
beam_sdk-0.15.14.dist-info/RECORD
