Metadata-Version: 2.1
Name: beam-sdk
Version: 0.15.14
Summary: 
Author: beam.cloud
Author-email: support@beam.cloud
Requires-Python: >=3.7,<4.0
Classifier: Programming Language :: Python :: 3
Classifier: Programming Language :: Python :: 3.7
Classifier: Programming Language :: Python :: 3.8
Classifier: Programming Language :: Python :: 3.9
Classifier: Programming Language :: Python :: 3.10
Classifier: Programming Language :: Python :: 3.11
Classifier: Programming Language :: Python :: 3.12
Requires-Dist: Jinja2 (>=3.1.2,<4.0.0)
Requires-Dist: astor (>=0.8.1,<0.9.0)
Requires-Dist: croniter (>=1.3.7,<2.0.0)
Requires-Dist: importlib-metadata (==5.2.0)
Requires-Dist: marshmallow (==3.18.0)
Requires-Dist: marshmallow-dataclass (>=8.5.9,<9.0.0)
Requires-Dist: typeguard (>=2.13.3,<3.0.0)
Requires-Dist: typing-extensions (>=4.7.1,<5.0.0)
Requires-Dist: validators (>=0.20.0,<0.21.0)
